{"aweme_infos":[{"aweme_info_type":1,"aweme_count":177}],"extra":{"now":1619804026000,"fatal_item_ids":[],"logid":"2021050101334501021216416356A56803"},"poi_info":{"user_count":17295,"cover_medium":{"uri":"46b700013ca4797326f1","url_list":["https://p5-ipv6.douyinpic.com/obj/46b700013ca4797326f1?from=1551292344","https://p29.douyinpic.com/obj/46b700013ca4797326f1?from=1551292344","https://p26.douyinpic.com/obj/46b700013ca4797326f1?from=1551292344"]},"show_type":1,"icon_service_type_list":null,"poi_name":"今天假日音乐餐吧","poi_longitude":116.274178,"poi_type":0,"poi_subtitle":"入围北京市烧烤热门榜","poi_frontend_type":[{"code":"010116","name":"美食;中式餐饮;烧烤"}],"collected_count":"1687","share_info":{"share_url":"https://www.iesdouyin.com/share/poilist/?id=6610336561605117960&u_code=17lgj7920","share_weibo_desc":"今天假日音乐餐吧附近超多有趣的抖音视频，一起来玩，戳这里","share_title":"今天假日音乐餐吧附近超多有趣的抖音视频，一起来玩，戳这里","bool_persist":0},"expand_type":1,"icon_on_entry":{"uri":"33a2200013bb98733b01e","url_list":["https://p9.douyinpic.com/obj/33a2200013bb98733b01e?from=1551292344","https://p5-ipv6.douyinpic.com/obj/33a2200013bb98733b01e?from=1551292344","https://p3.douyinpic.com/obj/33a2200013bb98733b01e?from=1551292344"]},"poi_subtitle_type":3,"distance":"","address_info":{"city":"北京市","district":"丰台区","address":"丰体北路甲2号(丰台体育馆北门)","simple_addr":"北京市丰台区丰体北路甲2号(丰台体育馆北门)","city_code":"110000","addr_with_extra_info":"北京市丰台区丰体北路甲2号(丰台体育馆北门)","province":"北京市"},"collect_stat":0,"poi_latitude":39.867039,"effect_ids":null,"item_count":655,"cover_hd":{"uri":"46b700013ca4797326f1","url_list":["https://p6.douyinpic.com/obj/46b700013ca4797326f1?from=1551292344","https://p29.douyinpic.com/obj/46b700013ca4797326f1?from=1551292344","https://p5-ipv6.douyinpic.com/obj/46b700013ca4797326f1?from=1551292344"]},"icon_type":12,"icon_on_map":{"uri":"9889002440fdbff2ac42","url_list":["https://p5-ipv6.douyinpic.com/obj/9889002440fdbff2ac42?from=1551292344","https://p11.douyinpic.com/obj/9889002440fdbff2ac42?from=1551292344","https://p3.douyinpic.com/obj/9889002440fdbff2ac42?from=1551292344"]},"poi_id":"6610336561605117960","cover_item":{"uri":"2ecd20001bf2f87ec1697","url_list":["https://p5-ipv6.douyinpic.com/obj/2ecd20001bf2f87ec1697?from=1551292344","https://p26.douyinpic.com/obj/2ecd20001bf2f87ec1697?from=1551292344","https://p6.douyinpic.com/obj/2ecd20001bf2f87ec1697?from=1551292344"]},"dou_landlord_info":{"landlord_item_bottom_icon_list":null},"voucher_release_areas":[],"cover_large":{"uri":"46b700013ca4797326f1","url_list":["https://p3.douyinpic.com/obj/46b700013ca4797326f1?from=1551292344","https://p26.douyinpic.com/obj/46b700013ca4797326f1?from=1551292344","https://p6.douyinpic.com/obj/46b700013ca4797326f1?from=1551292344"]},"cover_thumb":{"uri":"46b700013ca4797326f1","url_list":["https://p26.douyinpic.com/obj/46b700013ca4797326f1?from=1551292344","https://p11.douyinpic.com/obj/46b700013ca4797326f1?from=1551292344","https://p6.douyinpic.com/obj/46b700013ca4797326f1?from=1551292344"]},"poi_voucher":"","poi_backend_type":{"name":"美食;中式餐饮;烧烤","code":"010116"},"view_count":"564628","ext_json":"{\"item_ext\":{\"sub_type\":\"烧烤\",\"anchor_info\":{\"minor_tags\":[{\"content\":\"56.5w次看过\",\"type\":7,\"style\":0,\"priority\":-1},{\"content\":\"入围北京市烧烤热门榜\",\"type\":13,\"style\":1,\"priority\":0}],\"minor_tag_extend_time\":-1},\"anchor_comment\":{\"descs\":[\"56.5w次看过\"],\"gray_label\":\"入围北京市烧烤热门榜\"},\"rank_desc_list\":[\"入围北京市烧烤热门榜\"],\"poi_cover_list\":[{\"cover_image\":{\"uri\":\"2ecd20001bf2f87ec1697\",\"url_list\":[\"https://p26.douyinpic.com/obj/2ecd20001bf2f87ec1697?from=428053480\",\"https://p29.douyinpic.com/obj/2ecd20001bf2f87ec1697?from=428053480\",\"https://p6.douyinpic.com/obj/2ecd20001bf2f87ec1697?from=428053480\"]},\"source\":2}]}}","poi_detail_tags":null,"type_code":"050100","is_admin_area":false,"icon_on_info":{"uri":"9b930003835ca5c3f9e1","url_list":["https://p29.douyinpic.com/obj/9b930003835ca5c3f9e1?from=1551292344","https://p11.douyinpic.com/obj/9b930003835ca5c3f9e1?from=1551292344","https://p5-ipv6.douyinpic.com/obj/9b930003835ca5c3f9e1?from=1551292344"]}},"detail_struct_type":2,"poi_ext":{"poi_class_rank":{"city_code":"110000","poi_class_code":0,"backend_type":{},"rank_code":"FOOD_SHAOKAO","poi_id":"B0FFJF5B6B","class_option":{"code":0,"name":""},"description":"入围北京市烧烤热门榜","rank_value":28,"can_switch":1},"has_upload_image_permission":false,"customer_service_url":"aweme://webview/?url=https%3A%2F%2Faweme.snssdk.com%2Ffalcon%2Fpoi_h5%2Fmerchant_access_helper_center%3Fenter_from%3Dpoi_page","telephone":"13911780869;63860852;010-63860852;010-63868972","photos":[{"title":"","pic_large":{"uri":"2ecd20001bf2f87ec1697","url_list":["https://p11.douyinpic.com/obj/2ecd20001bf2f87ec1697?from=1551292344","https://p6.douyinpic.com/obj/2ecd20001bf2f87ec1697?from=1551292344","https://p5-ipv6.douyinpic.com/obj/2ecd20001bf2f87ec1697?from=1551292344"]},"pic_medium":{"uri":"2ecd20001bf2f87ec1697","url_list":["https://p5-ipv6.douyinpic.com/obj/2ecd20001bf2f87ec1697?from=1551292344","https://p29.douyinpic.com/obj/2ecd20001bf2f87ec1697?from=1551292344","https://p9.douyinpic.com/obj/2ecd20001bf2f87ec1697?from=1551292344"]},"tag_list":null},{"title":"","pic_large":{"uri":"2ec7d0000951aa3101684","url_list":["https://p26.douyinpic.com/obj/2ec7d0000951aa3101684?from=1551292344","https://p5-ipv6.douyinpic.com/obj/2ec7d0000951aa3101684?from=1551292344","https://p3.douyinpic.com/obj/2ec7d0000951aa3101684?from=1551292344"]},"pic_medium":{"uri":"2ec7d0000951aa3101684","url_list":["https://p5-ipv6.douyinpic.com/obj/2ec7d0000951aa3101684?from=1551292344","https://p26.douyinpic.com/obj/2ec7d0000951aa3101684?from=1551292344","https://p3.douyinpic.com/obj/2ec7d0000951aa3101684?from=1551292344"]},"tag_list":null},{"title":"","pic_large":{"uri":"2ece0000070595b8ec2ba","url_list":["https://p6.douyinpic.com/obj/2ece0000070595b8ec2ba?from=1551292344","https://p3.douyinpic.com/obj/2ece0000070595b8ec2ba?from=1551292344","https://p29.douyinpic.com/obj/2ece0000070595b8ec2ba?from=1551292344"]},"pic_medium":{"uri":"2ece0000070595b8ec2ba","url_list":["https://p6.douyinpic.com/obj/2ece0000070595b8ec2ba?from=1551292344","https://p5-ipv6.douyinpic.com/obj/2ece0000070595b8ec2ba?from=1551292344","https://p29.douyinpic.com/obj/2ece0000070595b8ec2ba?from=1551292344"]},"tag_list":null},{"title":"","pic_large":{"uri":"aweme-web-babel/boa3strhd179oghbnmr0","url_list":["https://p29.douyinpic.com/img/aweme-web-babel/boa3strhd179oghbnmr0~noop.jpeg?from=1551292344","https://p3.douyinpic.com/img/aweme-web-babel/boa3strhd179oghbnmr0~noop.jpeg?from=1551292344","https://p6.douyinpic.com/img/aweme-web-babel/boa3strhd179oghbnmr0~noop.jpeg?from=1551292344"]},"pic_medium":{"uri":"aweme-web-babel/boa3strhd179oghbnmr0","url_list":["https://p26.douyinpic.com/img/aweme-web-babel/boa3strhd179oghbnmr0~q40.jpeg?from=1551292344","https://p3.douyinpic.com/img/aweme-web-babel/boa3strhd179oghbnmr0~q40.jpeg?from=1551292344","https://p5-ipv6.douyinpic.com/img/aweme-web-babel/boa3strhd179oghbnmr0~q40.jpeg?from=1551292344"]},"tag_list":null},{"title":"","pic_large":{"uri":"aweme-web-babel/boa3svafl7tknnvhpmm0","url_list":["https://p5-ipv6.douyinpic.com/img/aweme-web-babel/boa3svafl7tknnvhpmm0~noop.jpeg?from=1551292344","https://p11.douyinpic.com/img/aweme-web-babel/boa3svafl7tknnvhpmm0~noop.jpeg?from=1551292344","https://p6.douyinpic.com/img/aweme-web-babel/boa3svafl7tknnvhpmm0~noop.jpeg?from=1551292344"]},"pic_medium":{"uri":"aweme-web-babel/boa3svafl7tknnvhpmm0","url_list":["https://p3.douyinpic.com/img/aweme-web-babel/boa3svafl7tknnvhpmm0~q40.jpeg?from=1551292344","https://p11.douyinpic.com/img/aweme-web-babel/boa3svafl7tknnvhpmm0~q40.jpeg?from=1551292344","https://p29.douyinpic.com/img/aweme-web-babel/boa3svafl7tknnvhpmm0~q40.jpeg?from=1551292344"]},"tag_list":null},{"title":"醉蟹钱","pic_large":{"uri":"aweme-web-babel/boa3pde6bi3rmukkm6ng","url_list":["https://p5-ipv6.douyinpic.com/img/aweme-web-babel/boa3pde6bi3rmukkm6ng~noop.jpeg?from=1551292344","https://p11.douyinpic.com/img/aweme-web-babel/boa3pde6bi3rmukkm6ng~noop.jpeg?from=1551292344","https://p3.douyinpic.com/img/aweme-web-babel/boa3pde6bi3rmukkm6ng~noop.jpeg?from=1551292344"]},"pic_medium":{"uri":"aweme-web-babel/boa3pde6bi3rmukkm6ng","url_list":["https://p11.douyinpic.com/img/aweme-web-babel/boa3pde6bi3rmukkm6ng~q40.jpeg?from=1551292344","https://p5-ipv6.douyinpic.com/img/aweme-web-babel/boa3pde6bi3rmukkm6ng~q40.jpeg?from=1551292344","https://p26.douyinpic.com/img/aweme-web-babel/boa3pde6bi3rmukkm6ng~q40.jpeg?from=1551292344"]},"tag_list":[]},{"title":"蒜香小排","pic_large":{"url_list":["https://p3.douyinpic.com/img/aweme-web-babel/boa3peafl7tknnvhpmh0~noop.jpeg?from=1551292344","https://p6.douyinpic.com/img/aweme-web-babel/boa3peafl7tknnvhpmh0~noop.jpeg?from=1551292344","https://p5-ipv6.douyinpic.com/img/aweme-web-babel/boa3peafl7tknnvhpmh0~noop.jpeg?from=1551292344"],"uri":"aweme-web-babel/boa3peafl7tknnvhpmh0"},"pic_medium":{"uri":"aweme-web-babel/boa3peafl7tknnvhpmh0","url_list":["https://p3.douyinpic.com/img/aweme-web-babel/boa3peafl7tknnvhpmh0~q40.jpeg?from=1551292344","https://p5-ipv6.douyinpic.com/img/aweme-web-babel/boa3peafl7tknnvhpmh0~q40.jpeg?from=1551292344","https://p26.douyinpic.com/img/aweme-web-babel/boa3peafl7tknnvhpmh0~q40.jpeg?from=1551292344"]},"tag_list":[]},{"title":"烤串","pic_large":{"uri":"aweme-web-babel/boa3q4o1t8a61hob7nh0","url_list":["https://p6.douyinpic.com/img/aweme-web-babel/boa3q4o1t8a61hob7nh0~noop.jpeg?from=1551292344","https://p3.douyinpic.com/img/aweme-web-babel/boa3q4o1t8a61hob7nh0~noop.jpeg?from=1551292344","https://p5-ipv6.douyinpic.com/img/aweme-web-babel/boa3q4o1t8a61hob7nh0~noop.jpeg?from=1551292344"]},"pic_medium":{"uri":"aweme-web-babel/boa3q4o1t8a61hob7nh0","url_list":["https://p3.douyinpic.com/img/aweme-web-babel/boa3q4o1t8a61hob7nh0~q40.jpeg?from=1551292344","https://p26.douyinpic.com/img/aweme-web-babel/boa3q4o1t8a61hob7nh0~q40.jpeg?from=1551292344","https://p5-ipv6.douyinpic.com/img/aweme-web-babel/boa3q4o1t8a61hob7nh0~q40.jpeg?from=1551292344"]},"tag_list":[]},{"pic_large":{"url_list":["https://p9.douyinpic.com/img/aweme-web-babel/bob9uvhc38vojin0h9hg~noop.jpeg?from=1551292344","https://p29.douyinpic.com/img/aweme-web-babel/bob9uvhc38vojin0h9hg~noop.jpeg?from=1551292344","https://p11.douyinpic.com/img/aweme-web-babel/bob9uvhc38vojin0h9hg~noop.jpeg?from=1551292344"],"uri":"aweme-web-babel/bob9uvhc38vojin0h9hg"},"pic_medium":{"uri":"aweme-web-babel/bob9uvhc38vojin0h9hg","url_list":["https://p5-ipv6.douyinpic.com/img/aweme-web-babel/bob9uvhc38vojin0h9hg~q40.jpeg?from=1551292344","https://p6.douyinpic.com/img/aweme-web-babel/bob9uvhc38vojin0h9hg~q40.jpeg?from=1551292344","https://p3.douyinpic.com/img/aweme-web-babel/bob9uvhc38vojin0h9hg~q40.jpeg?from=1551292344"]},"tag_list":[],"title":"烤鸡翅"},{"title":"小龙虾","pic_large":{"uri":"aweme-web-babel/bob9v382mk98etbp8j30","url_list":["https://p9.douyinpic.com/img/aweme-web-babel/bob9v382mk98etbp8j30~noop.jpeg?from=1551292344","https://p3.douyinpic.com/img/aweme-web-babel/bob9v382mk98etbp8j30~noop.jpeg?from=1551292344","https://p5-ipv6.douyinpic.com/img/aweme-web-babel/bob9v382mk98etbp8j30~noop.jpeg?from=1551292344"]},"pic_medium":{"uri":"aweme-web-babel/bob9v382mk98etbp8j30","url_list":["https://p11.douyinpic.com/img/aweme-web-babel/bob9v382mk98etbp8j30~q40.jpeg?from=1551292344","https://p9.douyinpic.com/img/aweme-web-babel/bob9v382mk98etbp8j30~q40.jpeg?from=1551292344","https://p5-ipv6.douyinpic.com/img/aweme-web-babel/bob9v382mk98etbp8j30~q40.jpeg?from=1551292344"]},"tag_list":[]},{"title":"蒜蓉烤扇贝","pic_large":{"uri":"aweme-web-babel/bob9v601t8a61hob81tg","url_list":["https://p9.douyinpic.com/img/aweme-web-babel/bob9v601t8a61hob81tg~noop.jpeg?from=1551292344","https://p11.douyinpic.com/img/aweme-web-babel/bob9v601t8a61hob81tg~noop.jpeg?from=1551292344","https://p3.douyinpic.com/img/aweme-web-babel/bob9v601t8a61hob81tg~noop.jpeg?from=1551292344"]},"pic_medium":{"uri":"aweme-web-babel/bob9v601t8a61hob81tg","url_list":["https://p29.douyinpic.com/img/aweme-web-babel/bob9v601t8a61hob81tg~q40.jpeg?from=1551292344","https://p11.douyinpic.com/img/aweme-web-babel/bob9v601t8a61hob81tg~q40.jpeg?from=1551292344","https://p3.douyinpic.com/img/aweme-web-babel/bob9v601t8a61hob81tg~q40.jpeg?from=1551292344"]},"tag_list":[]},{"title":"红柳羊肉串","pic_large":{"uri":"aweme-web-babel/bob9vb1c38vojin0h9i0","url_list":["https://p5-ipv6.douyinpic.com/img/aweme-web-babel/bob9vb1c38vojin0h9i0~noop.jpeg?from=1551292344","https://p11.douyinpic.com/img/aweme-web-babel/bob9vb1c38vojin0h9i0~noop.jpeg?from=1551292344","https://p3.douyinpic.com/img/aweme-web-babel/bob9vb1c38vojin0h9i0~noop.jpeg?from=1551292344"]},"pic_medium":{"uri":"aweme-web-babel/bob9vb1c38vojin0h9i0","url_list":["https://p26.douyinpic.com/img/aweme-web-babel/bob9vb1c38vojin0h9i0~q40.jpeg?from=1551292344","https://p5-ipv6.douyinpic.com/img/aweme-web-babel/bob9vb1c38vojin0h9i0~q40.jpeg?from=1551292344","https://p3.douyinpic.com/img/aweme-web-babel/bob9vb1c38vojin0h9i0~q40.jpeg?from=1551292344"]},"tag_list":[]},{"pic_large":{"uri":"aweme-web-babel/bob9vf7clj85c952miu0","url_list":["https://p29.douyinpic.com/img/aweme-web-babel/bob9vf7clj85c952miu0~noop.jpeg?from=1551292344","https://p5-ipv6.douyinpic.com/img/aweme-web-babel/bob9vf7clj85c952miu0~noop.jpeg?from=1551292344","https://p9.douyinpic.com/img/aweme-web-babel/bob9vf7clj85c952miu0~noop.jpeg?from=1551292344"]},"pic_medium":{"uri":"aweme-web-babel/bob9vf7clj85c952miu0","url_list":["https://p26.douyinpic.com/img/aweme-web-babel/bob9vf7clj85c952miu0~q40.jpeg?from=1551292344","https://p5-ipv6.douyinpic.com/img/aweme-web-babel/bob9vf7clj85c952miu0~q40.jpeg?from=1551292344","https://p11.douyinpic.com/img/aweme-web-babel/bob9vf7clj85c952miu0~q40.jpeg?from=1551292344"]},"tag_list":[],"title":"精酿啤酒"}],"recommend_items":null,"recommend_title":"推荐菜","has_detail_info":false,"sub_type":"烧烤","valid":true,"question_info":{"questions":[],"total_question_count":0},"poi_tag_info":{"user_comment_tag":null},"cost":"88","destination_poi_class_list":null,"feedback_url":"aweme/v1/poi/feedback","detail_info":{"head_title":"","end_title":"详情","detail_info_url":"aweme://webview/?hide_nav_bar=1&rn_schema=aweme%3A%2F%2Freactnative%2F%3Fbundle%3Dindex.js%26channel%3Dpoi_rn_client_poi_detail_tab%26enter_from%3Dpoi_page%26hide_nav_bar%3D1%26module_name%3Dpage_info%26more_detail%3D1%26poi_id%3D6610336561605117960%26show_qa%3D1&url=https%3A%2F%2Faweme.snssdk.com%2Ffalcon%2Fpoi_rn_client_web%2Fpoi_detail_tab%2Fpage_info%2F%3Fenter_from%3Dpoi_page%26hide_nav_bar%3D1%26more_detail%3D1%26poi_id%3D6610336561605117960%26show_qa%3D1","tags":null},"show_merchant_fix_prompt":false,"open_time":"10:00开始营业","comment_list":null,"biz_src":8,"poi_ranks":[{"rank_code":"POI_RANK_110000_FOOD_SHAOKAO","rank_desc":"入围北京市烧烤热门榜","schema_type":3,"schema_url":"aweme://webview/?hide_nav_bar=1&rn_schema=aweme%3A%2F%2Freactnative%2F%3Fbundle%3Dindex.js%26channel%3Dpoi_rn_client_common_rank%26enter_from%3Dpoi_page%26hide_nav_bar%3D1%26module_name%3Dpage_common_rank%26poi_backend_type%3D010116%26poi_device_samecity%3D1%26poi_id%3D6610336561605117960%26rank_code%3DPOI_RANK_110000_FOOD_SHAOKAO%26rank_type%3D1%26scene_type%3D4%26should_full_screen%3Dtrue&should_full_screen=true&url=https%3A%2F%2Faweme.snssdk.com%2Ffalcon%2Fpoi_rn_client_web%2Fcommon_rank%3Fenter_from%3Dpoi_page%26hide_nav_bar%3D1%26poi_backend_type%3D010116%26poi_device_samecity%3D1%26poi_id%3D6610336561605117960%26rank_code%3DPOI_RANK_110000_FOOD_SHAOKAO%26rank_type%3D1%26scene_type%3D4%26should_full_screen%3Dtrue","rank_type":1},{"schema_type":3,"schema_url":"aweme://webview/?hide_nav_bar=1&rn_schema=aweme%3A%2F%2Freactnative%2F%3Fbundle%3Dindex.js%26channel%3Dpoi_rn_client_common_rank%26enter_from%3Dpoi_page%26hide_nav_bar%3D1%26module_name%3Dpage_common_rank%26poi_backend_type%3D010116%26poi_device_samecity%3D1%26poi_id%3D6610336561605117960%26rank_code%3DPOI_SCENE_RANK_110000_qing_lv_bi_chi%26rank_type%3D2%26scene_type%3D4%26should_full_screen%3Dtrue&should_full_screen=true&url=https%3A%2F%2Faweme.snssdk.com%2Ffalcon%2Fpoi_rn_client_web%2Fcommon_rank%3Fenter_from%3Dpoi_page%26hide_nav_bar%3D1%26poi_backend_type%3D010116%26poi_device_samecity%3D1%26poi_id%3D6610336561605117960%26rank_code%3DPOI_SCENE_RANK_110000_qing_lv_bi_chi%26rank_type%3D2%26scene_type%3D4%26should_full_screen%3Dtrue","rank_type":2,"rank_code":"POI_SCENE_RANK_110000_qing_lv_bi_chi","rank_desc":"入围北京市情侣必吃榜"}]},"poi_list":null,"coupon_share_setting":{"share_text":"喊好友领优惠，一起去玩吧","share_flag":1},"icon_service_list":null,"aweme_title":"相关视频","status_code":0,"is_local":true,"user_list":[],"poi_owner":{"open_day":"0,0,0,0,0,0,0","enterprise_verify_reason":"","crypto_owner_id":"MS4wLjABAAAAi-8od8cP5lfORrNTW9IXNyw5-C2sihUw8zFDtCo4zGg","owner_id":"100525485192","owner_name":"北京今天假日饮食有限责任公司","avatar_url":"https://p9.douyinpic.com/aweme/100x100/2ec1100078c14a2c457fa.jpeg?from=4010531038","signature":"今天假日酒店是一家大型中餐厅，一楼是音乐餐吧，可以容纳200人的活动，听歌，撸串，聚会。二楼有一个可容纳300人的宴会厅可以举办各种婚宴，聚会，年会。有8个豪华包房，吃饭K歌。三楼有一个可以容纳150人的宴会厅，5个豪华包房。四楼是室内模拟高尔夫球场，欢迎各位光临"},"around_hot_poi_count":177,"poi_aweme_tab":[{"tab_id":0,"tab_name":"相关视频","tab_mob_name":"xiang_guang_shi_ping","tab_type":1}],"log_pb":{"impr_id":"2021050101334501021216416356A56803"},"status_msg":"","is_show_campus_rank":0,"show_detail_type":1,"notice_banner_list":null,"poi_claimer":{"sec_claimer_id":"MS4wLjABAAAAi-8od8cP5lfORrNTW9IXNyw5-C2sihUw8zFDtCo4zGg","enterprise_user":1,"can_claim":false},"poi_theme_list":null,"dynamic":[{"type":1,"id":1,"lynx_data":{"lynx_url":"aweme://lynxview/?bundle=poi_address%2Ftemplate.js&channel=poi_lynx_poi_detail_cell&dynamic=1&group=poi_lynx_poi_detail_cell","raw_data":"{\"title\":\"北京市丰台区丰体北路甲2号(丰台体育馆北门)\",\"sub_title\":\"距离您当前位置 13.5km\",\"intro\":\"\",\"poi_name\":\"今天假日音乐餐吧\",\"poi_address\":{\"province\":\"北京市\",\"city\":\"北京市\",\"district\":\"丰台区\",\"address\":\"丰体北路甲2号(丰台体育馆北门)\",\"simple_addr\":\"北京市丰台区丰体北路甲2号(丰台体育馆北门)\",\"city_code\":\"110000\",\"addr_with_extra_info\":\"北京市丰台区丰体北路甲2号(丰台体育馆北门)\"},\"poi_longitude\":116.274178,\"poi_latitude\":39.867039,\"show_navi\":\"true\"}"}},{"type":1,"id":15,"lynx_data":{"lynx_url":"aweme://lynxview/?bundle=ugc_comment_card%2Ftemplate.js&channel=poi_lynx_poi_detail_cell&dynamic=1&group=poi_lynx_poi_detail_cell","raw_data":"{\"title\":\"用户评价\",\"recommend_rate\":85,\"list_entry\":{\"schema_type\":4,\"schema_url\":\"aweme://lynxview/?bundle=ugc_rate_detail%2Ftemplate.js\\u0026channel=poi_lynx_poi_ugc\\u0026dynamic=1\\u0026group=poi_lynx_poi_ugc\\u0026hide_nav_bar=1\\u0026poi_id=6610336561605117960\"},\"labels\":[{\"type\":2,\"id\":1001100101,\"text\":\"还想再吃\",\"count\":4},{\"type\":2,\"id\":1001100501,\"text\":\"环境好\",\"count\":3},{\"type\":2,\"id\":1001100301,\"text\":\"有特色\",\"count\":2},{\"type\":2,\"id\":1001100601,\"text\":\"性价比高\",\"count\":1},{\"type\":2,\"id\":1001100401,\"text\":\"服务贴心\",\"count\":1},{\"type\":2,\"id\":1001100302,\"text\":\"分量足\",\"count\":1},{\"type\":2,\"id\":1001100201,\"text\":\"味道棒\",\"count\":1},{\"type\":2,\"id\":1001050601,\"text\":\"价格略贵\",\"count\":1},{\"type\":2,\"id\":1001050501,\"text\":\"环境还行\",\"count\":1},{\"type\":2,\"id\":1001050101,\"text\":\"没说的那么好\",\"count\":1}]}"}},{"type":0,"id":7}],"aweme_type":12,"aweme_list":null}
